Testsuite: comp207p.target.DynamicVariableFoldingTest
Tests run: 5, Failures: 0, Errors: 5, Skipped: 0, Time elapsed: 0.017 sec

Testcase: testMethodThree took 0.001 sec
	Caused an ERROR
Bad type on operand stack
Exception Details:
  Location:
    comp207p/target/DynamicVariableFolding.methodFour()I @15: invokevirtual
  Reason:
    Type double_2nd (current frame, stack[5]) is not assignable to 'java/io/PrintStream'
  Current Frame:
    bci: @15
    flags: { }
    locals: { 'comp207p/target/DynamicVariableFolding' }
    stack: { integer, integer, 'java/io/PrintStream', integer, double, double_2nd, double, double_2nd }
  Bytecode:
    0x0000000: 1205 1239 b200 0312 0512 3a87 1400 3bb6
    0x0000010: 0009 1234 123d 123e 123d 123e 123f ac  

java.lang.VerifyError: Bad type on operand stack
Exception Details:
  Location:
    comp207p/target/DynamicVariableFolding.methodFour()I @15: invokevirtual
  Reason:
    Type double_2nd (current frame, stack[5]) is not assignable to 'java/io/PrintStream'
  Current Frame:
    bci: @15
    flags: { }
    locals: { 'comp207p/target/DynamicVariableFolding' }
    stack: { integer, integer, 'java/io/PrintStream', integer, double, double_2nd, double, double_2nd }
  Bytecode:
    0x0000000: 1205 1239 b200 0312 0512 3a87 1400 3bb6
    0x0000010: 0009 1234 123d 123e 123d 123e 123f ac  

	at comp207p.target.DynamicVariableFoldingTest.<init>(Unknown Source)
	at java.lang.reflect.Constructor.newInstance(Constructor.java:423)

Testcase: testMethodFour took 0 sec
	Caused an ERROR
Bad type on operand stack
Exception Details:
  Location:
    comp207p/target/DynamicVariableFolding.methodFour()I @15: invokevirtual
  Reason:
    Type double_2nd (current frame, stack[5]) is not assignable to 'java/io/PrintStream'
  Current Frame:
    bci: @15
    flags: { }
    locals: { 'comp207p/target/DynamicVariableFolding' }
    stack: { integer, integer, 'java/io/PrintStream', integer, double, double_2nd, double, double_2nd }
  Bytecode:
    0x0000000: 1205 1239 b200 0312 0512 3a87 1400 3bb6
    0x0000010: 0009 1234 123d 123e 123d 123e 123f ac  

java.lang.VerifyError: Bad type on operand stack
Exception Details:
  Location:
    comp207p/target/DynamicVariableFolding.methodFour()I @15: invokevirtual
  Reason:
    Type double_2nd (current frame, stack[5]) is not assignable to 'java/io/PrintStream'
  Current Frame:
    bci: @15
    flags: { }
    locals: { 'comp207p/target/DynamicVariableFolding' }
    stack: { integer, integer, 'java/io/PrintStream', integer, double, double_2nd, double, double_2nd }
  Bytecode:
    0x0000000: 1205 1239 b200 0312 0512 3a87 1400 3bb6
    0x0000010: 0009 1234 123d 123e 123d 123e 123f ac  

	at comp207p.target.DynamicVariableFoldingTest.<init>(Unknown Source)
	at java.lang.reflect.Constructor.newInstance(Constructor.java:423)

Testcase: testMethodOne took 0 sec
	Caused an ERROR
Bad type on operand stack
Exception Details:
  Location:
    comp207p/target/DynamicVariableFolding.methodFour()I @15: invokevirtual
  Reason:
    Type double_2nd (current frame, stack[5]) is not assignable to 'java/io/PrintStream'
  Current Frame:
    bci: @15
    flags: { }
    locals: { 'comp207p/target/DynamicVariableFolding' }
    stack: { integer, integer, 'java/io/PrintStream', integer, double, double_2nd, double, double_2nd }
  Bytecode:
    0x0000000: 1205 1239 b200 0312 0512 3a87 1400 3bb6
    0x0000010: 0009 1234 123d 123e 123d 123e 123f ac  

java.lang.VerifyError: Bad type on operand stack
Exception Details:
  Location:
    comp207p/target/DynamicVariableFolding.methodFour()I @15: invokevirtual
  Reason:
    Type double_2nd (current frame, stack[5]) is not assignable to 'java/io/PrintStream'
  Current Frame:
    bci: @15
    flags: { }
    locals: { 'comp207p/target/DynamicVariableFolding' }
    stack: { integer, integer, 'java/io/PrintStream', integer, double, double_2nd, double, double_2nd }
  Bytecode:
    0x0000000: 1205 1239 b200 0312 0512 3a87 1400 3bb6
    0x0000010: 0009 1234 123d 123e 123d 123e 123f ac  

	at comp207p.target.DynamicVariableFoldingTest.<init>(Unknown Source)
	at java.lang.reflect.Constructor.newInstance(Constructor.java:423)

Testcase: testMethodTwoReturn took 0 sec
	Caused an ERROR
Bad type on operand stack
Exception Details:
  Location:
    comp207p/target/DynamicVariableFolding.methodFour()I @15: invokevirtual
  Reason:
    Type double_2nd (current frame, stack[5]) is not assignable to 'java/io/PrintStream'
  Current Frame:
    bci: @15
    flags: { }
    locals: { 'comp207p/target/DynamicVariableFolding' }
    stack: { integer, integer, 'java/io/PrintStream', integer, double, double_2nd, double, double_2nd }
  Bytecode:
    0x0000000: 1205 1239 b200 0312 0512 3a87 1400 3bb6
    0x0000010: 0009 1234 123d 123e 123d 123e 123f ac  

java.lang.VerifyError: Bad type on operand stack
Exception Details:
  Location:
    comp207p/target/DynamicVariableFolding.methodFour()I @15: invokevirtual
  Reason:
    Type double_2nd (current frame, stack[5]) is not assignable to 'java/io/PrintStream'
  Current Frame:
    bci: @15
    flags: { }
    locals: { 'comp207p/target/DynamicVariableFolding' }
    stack: { integer, integer, 'java/io/PrintStream', integer, double, double_2nd, double, double_2nd }
  Bytecode:
    0x0000000: 1205 1239 b200 0312 0512 3a87 1400 3bb6
    0x0000010: 0009 1234 123d 123e 123d 123e 123f ac  

	at comp207p.target.DynamicVariableFoldingTest.<init>(Unknown Source)
	at java.lang.reflect.Constructor.newInstance(Constructor.java:423)

Testcase: testMethodTwoOut took 0 sec
	Caused an ERROR
Bad type on operand stack
Exception Details:
  Location:
    comp207p/target/DynamicVariableFolding.methodFour()I @15: invokevirtual
  Reason:
    Type double_2nd (current frame, stack[5]) is not assignable to 'java/io/PrintStream'
  Current Frame:
    bci: @15
    flags: { }
    locals: { 'comp207p/target/DynamicVariableFolding' }
    stack: { integer, integer, 'java/io/PrintStream', integer, double, double_2nd, double, double_2nd }
  Bytecode:
    0x0000000: 1205 1239 b200 0312 0512 3a87 1400 3bb6
    0x0000010: 0009 1234 123d 123e 123d 123e 123f ac  

java.lang.VerifyError: Bad type on operand stack
Exception Details:
  Location:
    comp207p/target/DynamicVariableFolding.methodFour()I @15: invokevirtual
  Reason:
    Type double_2nd (current frame, stack[5]) is not assignable to 'java/io/PrintStream'
  Current Frame:
    bci: @15
    flags: { }
    locals: { 'comp207p/target/DynamicVariableFolding' }
    stack: { integer, integer, 'java/io/PrintStream', integer, double, double_2nd, double, double_2nd }
  Bytecode:
    0x0000000: 1205 1239 b200 0312 0512 3a87 1400 3bb6
    0x0000010: 0009 1234 123d 123e 123d 123e 123f ac  

	at comp207p.target.DynamicVariableFoldingTest.<init>(Unknown Source)
	at java.lang.reflect.Constructor.newInstance(Constructor.java:423)

